LICENSE
MANIFEST.in
README.md
setup.cfg
setup.py
dbhelpers/__init__.py
dbhelpers/connections.py
dbhelpers/helpers.py
dbhelpers.egg-info/PKG-INFO
dbhelpers.egg-info/SOURCES.txt
dbhelpers.egg-info/dependency_links.txt
dbhelpers.egg-info/not-zip-safe
dbhelpers.egg-info/top_level.txt